python_mouse_lerp_zuckemn/__init__.py
python_mouse_lerp_zuckemn/mouse_lerp.py
python_mouse_lerp_zuckemn-0.0.1.dist-info/LICENSE
python_mouse_lerp_zuckemn-0.0.1.dist-info/METADATA
python_mouse_lerp_zuckemn-0.0.1.dist-info/WHEEL
python_mouse_lerp_zuckemn-0.0.1.dist-info/top_level.txt
python_mouse_lerp_zuckemn-0.0.1.dist-info/RECORD
